.gitignore
.travis.yml
AUTHORS.rst
CONTRIBUTING.rst
HISTORY.rst
LICENSE
MANIFEST.in
Makefile
README.rst
requirements.txt
setup.cfg
setup.py
tox.ini
docs/Makefile
docs/authors.rst
docs/conf.py
docs/contributing.rst
docs/history.rst
docs/index.rst
docs/installation.rst
docs/make.bat
docs/readme.rst
docs/usage.rst
kyos/__init__.py
kyos/cli.py
kyos/features.py
kyos/nn.py
kyos.egg-info/PKG-INFO
kyos.egg-info/SOURCES.txt
kyos.egg-info/dependency_links.txt
kyos.egg-info/entry_points.txt
kyos.egg-info/not-zip-safe
kyos.egg-info/requires.txt
kyos.egg-info/top_level.txt
scripts/qsub-create_tabular.sh
scripts/run-art.py
scripts/run-art.sh
scripts/run-merge-tabular.sh
scripts/run-snp-mutator.sh
scripts/run-snp-pipeline.sh
scripts/snppipeline.mapq10.conf
tests/__init__.py
tests/test_cli.py
tests/test_features.py
tests/test_nn.py