Metadata-Version: 1.1
Name: kyos
Version: 0.2.0
Summary: Tools for haploid variant calling with Deep Neural Networks.
Home-page: https://github.com/CFSAN-Biostatistics/kyos
Author: Nathan Xue
Author-email: xue.nathanv1.0@gmail.com
License: BSD
Keywords: bioinformatics,NGS,kyos
Platform: UNKNOWN
Classifier: Development Status :: 2 - Pre-Alpha
Classifier: Intended Audience :: Developers
Classifier: License :: OSI Approved :: BSD License
Classifier: Natural Language :: English
Classifier: Programming Language :: Python :: 2
Classifier: Programming Language :: Python :: 2.7
Classifier: Programming Language :: Python :: 3
Classifier: Programming Language :: Python :: 3.4
Classifier: Programming Language :: Python :: 3.5
Classifier: Programming Language :: Python :: 3.6
